LICENSE
MANIFEST.in
README.md
requirements.txt
setup.cfg
setup.py
ibeam/__init__.py
ibeam/config.py
ibeam/ibeam_starter.py
ibeam.egg-info/PKG-INFO
ibeam.egg-info/SOURCES.txt
ibeam.egg-info/dependency_links.txt
ibeam.egg-info/requires.txt
ibeam.egg-info/top_level.txt
ibeam/src/__init__.py
ibeam/src/gateway_client.py
ibeam/src/health_server.py
ibeam/src/logs.py
ibeam/src/two_fa_selector.py
ibeam/src/var.py
ibeam/src/handlers/__init__.py
ibeam/src/handlers/http_handler.py
ibeam/src/handlers/inputs_handler.py
ibeam/src/handlers/login_handler.py
ibeam/src/handlers/process_handler.py
ibeam/src/handlers/secrets_handler.py
ibeam/src/handlers/strategy_handler.py
ibeam/src/login/__init__.py
ibeam/src/login/driver.py
ibeam/src/login/targets.py
ibeam/src/two_fa_handlers/__init__.py
ibeam/src/two_fa_handlers/external_request_handler.py
ibeam/src/two_fa_handlers/google_msg_handler.py
ibeam/src/two_fa_handlers/notification_resend_handler.py
ibeam/src/two_fa_handlers/two_fa_handler.py
ibeam/src/utils/__init__.py
ibeam/src/utils/py_utils.py
ibeam/src/utils/selenium_utils.py