Metadata-Version: 2.1
Name: ibeam
Version: 0.5.8
Summary: IBeam is an authentication and maintenance tool used for the Interactive Brokers Client Portal Web API Gateway.
Home-page: https://github.com/Voyz/ibeam
Author: Voy Zan
Author-email: voy1982@yahoo.co.uk
License: Apache-2.0
Keywords: interactive brokers,algo trading,algorithmic trading,data flow,quant,trading
Classifier: Development Status :: 4 - Beta
Classifier: Intended Audience :: Developers
Classifier: Topic :: Software Development :: Libraries :: Python Modules
Classifier: Programming Language :: Python :: 3.7
License-File: LICENSE
Requires-Dist: selenium==4.12.*
Requires-Dist: cryptography==40.0.*
Requires-Dist: pyvirtualdisplay==3.0.*
Requires-Dist: apscheduler==3.10.*
Requires-Dist: psutil==5.9.*
Requires-Dist: requests==2.31.*
Requires-Dist: pillow==9.5.*
